{
  "fileName": "Route.ts",
  "filePath": "zdk/src/entities/Route.ts",
  "url": "zoo-labs/zoo/blob/master/zdk/src/entities/Route.ts",
  "summary": "The code defines a class called `Route` that represents a trading route between two currencies. The purpose of this class is to calculate the mid-price of the trading route, which is the price at which the input currency can be exchanged for the output currency. The class takes in an array of `Pair` objects, which represent the pairs of tokens that can be traded along the route. It also takes in the input and output currencies, which are represented by `TInput` and `TOutput` respectively.\n\nThe constructor of the `Route` class performs several checks to ensure that the input and output currencies are valid for the given trading pairs. It checks that the pairs array is not empty, that all pairs have the same chain ID, that the input currency is involved in the first pair, and that the output currency is involved in the last pair (if it is defined).\n\nThe `midPrice` property of the `Route` class calculates the mid-price of the trading route. It does this by iterating over the pairs array and constructing a `Price` object for each pair. The `Price` object represents the price of one token in terms of another token. The `midPrice` property then multiplies all of the `Price` objects together to get the total price of the trading route. Finally, it constructs a new `Price` object that represents the mid-price of the trading route.\n\nThe `chainId` property of the `Route` class returns the chain ID of the first pair in the pairs array.\n\nThis class can be used in the larger project to calculate the mid-price of a trading route between two currencies. This information can be used to determine the optimal trading path for a given trade. For example, if a user wants to trade currency A for currency B, they can use the `Route` class to calculate the mid-price of the trading route between A and B. They can then compare this price to the prices of other trading routes to determine the most cost-effective path for their trade.",
  "questions": "1. What is the purpose of the `Route` class?\n- The `Route` class represents a route between two currencies in a decentralized exchange and contains information about the pairs involved in the route, the input and output currencies, and the mid price of the route.\n\n2. What is the significance of the `invariant` function calls in the constructor?\n- The `invariant` function calls ensure that certain conditions are met before the `Route` object is created, such as the length of the `pairs` array being greater than 0, all pairs having the same `chainId`, and the `input` currency being involved in the first pair in the route.\n\n3. What is the purpose of the `midPrice` property and how is it calculated?\n- The `midPrice` property calculates the mid price of the route, which is the geometric mean of the prices of all pairs in the route. It does this by iterating through the pairs and constructing a `Price` object for each pair, then multiplying all the prices together to get the final mid price.",
  "checksum": "563b0b7b57a8bb32d1f3cfbd64ed7612"
}