{
  "fileName": "common.d.ts",
  "filePath": "contracts/types/common.d.ts",
  "url": "zoo-labs/zoo/blob/master/contracts/types/common.d.ts",
  "summary": "This file contains interfaces and types related to event filtering and listening in the context of the Ethereum blockchain. The code is written in TypeScript and imports from the ethers.js library, which is a popular library for interacting with the Ethereum blockchain.\n\nThe `TypedEventFilter` interface extends the `EventFilter` interface from ethers.js and is used to define a filter for a specific event type. The `TypedEvent` interface extends the `Event` interface from ethers.js and is used to define an event with a specific set of arguments. The `args` property of the `TypedEvent` interface is of type `EventArgs`, which is a generic type that extends the `Result` interface from ethers.js.\n\nThe `TypedListener` type is a function type that takes in an array of event arguments and a `TypedEvent` object with the same set of arguments. This type is used to define a listener function that can be used to handle events of a specific type.\n\nThe `MinEthersFactory` type is a generic type that takes in two type parameters: `C` and `ARGS`. It is used to define a factory function that can be used to deploy a contract to the Ethereum blockchain. The `GetContractTypeFromFactory` type is a conditional type that extracts the contract type from a `MinEthersFactory` type. The `GetARGsTypeFromFactory` type is a conditional type that extracts the argument types from a `MinEthersFactory` type.\n\nOverall, this file provides useful interfaces and types for working with events and contracts in the context of the Ethereum blockchain. These interfaces and types can be used in other parts of the larger project to define event filters, event listeners, and contract factories. For example, the `TypedEventFilter` interface can be used to define a filter for a specific event type, and the `TypedListener` type can be used to define a listener function that handles events of that type. The `MinEthersFactory` type can be used to define a factory function that deploys a contract to the blockchain.",
  "questions": "1. What is the purpose of this code?\n   This code defines interfaces and types related to event filtering and listening, as well as contract deployment and argument types.\n\n2. What external dependencies does this code rely on?\n   This code imports the `EventFilter` and `Event` interfaces from the `ethers` library, as well as the `Result` type from the `@ethersproject/abi` library.\n\n3. How might this code be used in a larger project?\n   This code could be used to define and enforce types for event filtering and listening, as well as contract deployment and argument types, in a larger Ethereum-based project.",
  "checksum": "402647cc7e6809224ea323971eb5bfd3"
}