{
  "fileName": "IERC20Metadata.d.ts",
  "filePath": "contracts/types/IERC20Metadata.d.ts",
  "url": "zoo-labs/zoo/blob/master/contracts/types/IERC20Metadata.d.ts",
  "summary": "The code is an autogenerated file that defines an interface for an ERC20 token contract. The interface is called IERC20Metadata and it extends the BaseContract class from the ethers library. The interface defines the functions and events that are expected to be implemented by a contract that conforms to the ERC20 standard. \n\nThe ERC20 standard is a widely adopted standard for fungible tokens on the Ethereum blockchain. It defines a set of functions and events that a contract must implement in order to be considered an ERC20 token. The functions include transferring tokens, approving spending of tokens, and checking balances. The events include Transfer and Approval events that are emitted when tokens are transferred or approved for spending.\n\nThe IERC20Metadata interface defines the following functions: \n- allowance: returns the amount of tokens that an owner has approved for a spender to spend.\n- approve: approves a spender to spend a certain amount of tokens on behalf of the owner.\n- balanceOf: returns the balance of tokens for a given account.\n- decimals: returns the number of decimal places used by the token.\n- name: returns the name of the token.\n- symbol: returns the symbol of the token.\n- totalSupply: returns the total supply of the token.\n- transfer: transfers a certain amount of tokens from the sender's account to a recipient's account.\n- transferFrom: transfers a certain amount of tokens from one account to another, if the sender has been approved to spend those tokens.\n\nThe interface also defines two events: \n- Approval: emitted when a spender is approved to spend tokens on behalf of an owner.\n- Transfer: emitted when tokens are transferred from one account to another.\n\nThe IERC20Metadata interface can be used by other contracts or applications to interact with an ERC20 token contract. For example, a decentralized exchange (DEX) could use the IERC20Metadata interface to interact with a token contract in order to list the token on the exchange and allow users to trade the token. \n\nHere is an example of how the transfer function could be used to transfer tokens from one account to another: \n\n```\nimport { ethers } from 'ethers';\nimport { IERC20Metadata } from './IERC20Metadata';\n\nconst provider = new ethers.providers.JsonRpcProvider();\nconst signer = provider.getSigner();\n\nconst tokenAddress = '0x123...'; // address of the ERC20 token contract\nconst token = new ethers.Contract(tokenAddress, IERC20Metadata.interface, signer);\n\nconst recipientAddress = '0x456...'; // address of the recipient\nconst amount = ethers.utils.parseEther('10'); // amount of tokens to transfer\n\nconst tx = await token.transfer(recipientAddress, amount);\nawait tx.wait();\nconsole.log('Tokens transferred successfully!');\n```",
  "questions": "1. What is the purpose of this code?\n- This code defines an interface for an ERC20 token contract, including functions for transferring tokens, checking balances, and approving token transfers.\n\n2. What external libraries or dependencies does this code rely on?\n- This code relies on the ethers library for interacting with Ethereum, as well as the @ethersproject/bytes and @ethersproject/providers libraries.\n\n3. What events can be emitted by this contract?\n- This contract can emit two events: \"Approval\" and \"Transfer\". The \"Approval\" event is emitted when a token transfer is approved, and the \"Transfer\" event is emitted when tokens are transferred between accounts.",
  "checksum": "4f9d3e49a5ad81c768e8e0840961a0a3"
}