{
  "fileName": "validateSolidityTypeInstance.ts",
  "filePath": "zdk/src/functions/validateSolidityTypeInstance.ts",
  "url": "zoo-labs/zoo/blob/master/zdk/src/functions/validateSolidityTypeInstance.ts",
  "summary": "The code in this file defines a function called `validateSolidityTypeInstance` that is used to validate whether a given value is a valid instance of a Solidity type. The function takes two arguments: `value`, which is the value to be validated, and `solidityType`, which is the type of the value being validated.\n\nThe function first imports two constants from a file called `constants`: `SOLIDITY_TYPE_MAXIMA`, which is an object that maps Solidity types to their maximum values, and `ZERO`, which is a JSBI instance representing the value 0.\n\nNext, the function imports two external libraries: `JSBI`, which is a library for working with large integers in JavaScript, and `invariant`, which is a library for asserting conditions.\n\nThe function then uses the `invariant` library to check whether the `value` argument is greater than or equal to 0 and less than or equal to the maximum value for the given `solidityType`. If either of these conditions is not met, an error is thrown with a message indicating that the value is not a valid instance of the given Solidity type.\n\nThis function is likely used throughout the larger project to ensure that values passed to functions or stored in variables are valid instances of the expected Solidity types. For example, if a function expects an argument of type `uint256`, it could call `validateSolidityTypeInstance` to ensure that the argument is a valid instance of that type before proceeding with its logic.\n\nHere is an example usage of the `validateSolidityTypeInstance` function:\n\n```\nimport { validateSolidityTypeInstance, SolidityType } from 'zoo'\n\nconst myValue = JSBI.BigInt(100)\nconst myType = SolidityType.uint256\n\nvalidateSolidityTypeInstance(myValue, myType) // no error thrown\n\nconst invalidValue = JSBI.BigInt(-1)\n\nvalidateSolidityTypeInstance(invalidValue, myType) // throws an error: \"-1 is not a uint256.\"\n```",
  "questions": "1. What is the purpose of the `validateSolidityTypeInstance` function?\n- The `validateSolidityTypeInstance` function is used to validate whether a given `value` is a valid instance of a specified `solidityType`.\n\n2. What is the `JSBI` library used for in this code?\n- The `JSBI` library is used to perform mathematical operations on large integers, which are commonly used in Solidity smart contracts.\n\n3. What is the `invariant` library used for in this code?\n- The `invariant` library is used to throw an error if a certain condition is not met, in this case, if the `value` is not a valid instance of the specified `solidityType`.",
  "checksum": "f5bd8d8d5148dc31a305eba02f593d1a"
}